KittenGen/__init__.py
KittenGen/__main__.py
KittenGen/app.py
KittenGen/lib.py
KittenGen/static/css/bootstrap.min.css
KittenGen/static/css/codemirror.min.css
KittenGen/static/css/github-dark.min.css
KittenGen/static/js/bootstrap.min.js
KittenGen/static/js/clike.min.js
KittenGen/static/js/codemirror.min.js
KittenGen/static/js/cpp.min.js
KittenGen/static/js/highlight.min.js
KittenGen/static/js/jquery.min.js
KittenGen/static/js/python.min.js
KittenGen/templates/cyaron.html
KittenGen/templates/help.html
KittenGen/templates/index.html
KittenGen-1.2.1.dist-info/LICENSE
KittenGen-1.2.1.dist-info/METADATA
KittenGen-1.2.1.dist-info/WHEEL
KittenGen-1.2.1.dist-info/top_level.txt
KittenGen-1.2.1.dist-info/RECORD
