Metadata-Version: 2.1
Name: KittenGen
Version: 1.2.1
Author: stripe-python
Author-email: stripe-python@139.com
Maintainer: stripe-python
Maintainer-email: stripe-python@139.com
License: MIT License
Classifier: Programming Language :: Python :: 3
Classifier: License :: OSI Approved :: MIT License
Classifier: Operating System :: OS Independent
License-File: LICENSE
Requires-Dist: flask
Requires-Dist: jinja2
Requires-Dist: cyaron
